app/__main__.py
app/config.py
app/core.py
app/qq.py
app/ui.py
app/utils/__init__.py
app/utils/common.py
app/utils/log.py
nonencm-0.2.4.dist-info/METADATA
nonencm-0.2.4.dist-info/WHEEL
nonencm-0.2.4.dist-info/entry_points.txt
nonencm-0.2.4.dist-info/top_level.txt
nonencm-0.2.4.dist-info/RECORD
