Metadata-Version: 2.4
Name: nonencm
Version: 0.2.4
Summary: Add your description here
Requires-Python: >=3.11
Requires-Dist: loguru
Requires-Dist: mutagen
Requires-Dist: noneprompt
Requires-Dist: pillow
Requires-Dist: pyncm>=1.8.1
Requires-Dist: pyyaml
Requires-Dist: qqmusic-api-python>=0.3.6
Requires-Dist: segno
Provides-Extra: build
Requires-Dist: pyinstaller>=6.0.0; extra == "build"
Provides-Extra: pil-utils
Requires-Dist: pil-utils>=0.2.0; extra == "pil-utils"
Requires-Dist: typing_extensions>=4.8.0; extra == "pil-utils"
